{
  "id": "22387",
  "title": "ARIEL MISSING ERIC",
  "slug": "ariel-missing-eric",
  "description": "Eric and Ariel is a lovely couple Eric is going to another country for stydy and Ariel will miss him so much Rapunzel and Cinderella try their best to make her feel a little bit happier They have a great plan called Mermaid cheer up All of them are going to go shopping dressing up and dancing all night Fun isnt it",
  "instructions": "",
  "url": "https://html5.gamemonetize.com/88lfis9qrt1wen0ad5wwdq9dip5qkfy6/",
  "category": "Soccer",
  "categorySlug": "soccer",
  "tags": [
    "Dress Up",
    "Fashion",
    "Girl",
    "Girls",
    "Princess"
  ],
  "thumb": "https://img.gamemonetize.com/88lfis9qrt1wen0ad5wwdq9dip5qkfy6/512x384.jpg",
  "width": 800,
  "height": 600,
  "publisher": "OnlineGamess",
  "crawledAt": "2026-02-02T13:03:32.696Z"
}