{
  "model": {
    "version": 2,
    "nodes": [
      {
        "name": "RootNode",
        "position": [
          0,
          0,
          0
        ],
        "rotation": [
          0,
          0,
          0
        ],
        "scale": [
          1,
          1,
          1
        ],
        "scaleCompensation": false
      },
      {
        "name": "Paris_RoofRunners:2mSteps_03",
        "position": [
          0,
          0,
          0
        ],
        "rotation": [
          0.00000933467,
          0,
          0
        ],
        "scale": [
          0.01,
          0.01,
          0.01
        ],
        "scaleCompensation": false
      }
    ],
    "parents": [
      -1,
      0
    ],
    "skins": [],
    "morphs": [],
    "vertices": [
      {
        "position": {
          "type": "float32",
          "components": 3,
          "data": [
            -36.012,
            194.557,
            -16.778,
            -39.0526,
            195.093,
            41.2267,
            -33.9298,
            186.509,
            40.9611,
            -30.8892,
            185.973,
            -17.0436,
            -357.48,
            2.65118,
            32.6561,
            -348.123,
            -2.02097,
            -30.2718,
            -352.357,
            -5.93296,
            32.3905,
            -353.246,
            6.56318,
            -30.0062,
            -34.3429,
            194.966,
            -84.0146,
            -37.8679,
            197.123,
            -26.0749,
            -32.7194,
            188.551,
            -26.0567,
            -29.1945,
            186.393,
            -83.9963,
            -355.683,
            3.56822,
            -31.8532,
            -345.79,
            -2.84314,
            -94.5455,
            -350.535,
            -5.00469,
            -31.835,
            -350.938,
            5.72977,
            -94.5638,
            -353.611,
            1.13564,
            103.246,
            -348.861,
            -4.96683,
            45.4267,
            -348.378,
            -7.38301,
            103.461,
            -354.095,
            3.55181,
            45.2118,
            -39.6819,
            195.013,
            107.039,
            -30.5533,
            187.861,
            44.4622,
            -35.7867,
            196.379,
            44.2473,
            -34.4486,
            186.494,
            107.254,
            -58.6808,
            172.5,
            -97.8509,
            -58.6808,
            7.47332e-7,
            -85.5183,
            -58.6808,
            172.5,
            -85.5183,
            -58.6808,
            3.41989e-7,
            -97.8509,
            -58.6808,
            5.97503e-7,
            120.072,
            -58.6808,
            172.5,
            120.072,
            -58.6808,
            172.5,
            107.74,
            -58.6808,
            0,
            107.74,
            -56.2009,
            161.25,
            -85.5184,
            -56.2009,
            104.294,
            2.44568,
            -56.2009,
            161.25,
            -68.0447,
            -56.2009,
            110.437,
            8.27449,
            -56.2009,
            98.1522,
            8.27449,
            -56.2009,
            104.294,
            14.1033,
            -56.1808,
            168.75,
            -85.5184,
            -56.1808,
            168.75,
            107.74,
            -56.2009,
            161.25,
            90.567,
            -56.2009,
            47.3393,
            -68.0447,
            -56.2009,
            47.3393,
            -85.5184,
            -56.1808,
            39.8393,
            -85.5184,
            -56.2009,
            104.294,
            2.44568,
            -56.2009,
            98.1522,
            8.27449,
            -56.1808,
            39.8393,
            107.74,
            -56.2009,
            47.3393,
            90.567,
            -56.2009,
            161.25,
            90.567,
            -56.2009,
            110.437,
            8.27449,
            -56.2009,
            104.294,
            14.1033,
            -56.2009,
            161.25,
            107.74,
            -56.1808,
            168.75,
            107.74,
            -56.2009,
            47.3393,
            107.74,
            -56.2009,
            104.294,
            14.1033,
            -56.2009,
            47.3393,
            90.567,
            -56.2009,
            98.1522,
            8.27449,
            -56.1808,
            39.8393,
            107.74,
            -48.7279,
            161.25,
            90.567,
            -48.7279,
            110.437,
            8.27449,
            -56.2009,
            161.25,
            90.567,
            -56.2009,
            110.437,
            8.27449,
            -56.2009,
            161.25,
            -68.0447,
            -56.2009,
            110.437,
            8.27449,
            -48.7279,
            110.437,
            8.27449,
            -48.7279,
            161.25,
            -68.0447,
            -48.7279,
            104.294,
            2.44568,
            -48.7279,
            47.3393,
            -85.5184,
            -56.2009,
            104.294,
            2.44568,
            -56.2009,
            47.3393,
            -85.5184,
            -48.7279,
            47.3393,
            107.74,
            -48.7279,
            104.294,
            14.1033,
            -56.2009,
            47.3393,
            107.74,
            -56.2009,
            104.294,
            14.1033,
            -39.0526,
            195.093,
            41.2267,
            -353.246,
            6.56318,
            -30.0062,
            -357.48,
            2.65118,
            32.6561,
            -36.012,
            194.557,
            -16.778,
            -37.8679,
            197.123,
            -26.0749,
            -350.938,
            5.72977,
            -94.5638,
            -355.683,
            3.56822,
            -31.8532,
            -34.3429,
            194.966,
            -84.0146,
            -35.7867,
            196.379,
            44.2473,
            -354.095,
            3.55181,
            45.2118,
            -39.6819,
            195.013,
            107.039,
            -353.611,
            1.13564,
            103.246,
            -58.6808,
            172.5,
            -85.5183,
            -46.1808,
            172.5,
            -85.5183,
            -58.6808,
            172.5,
            -97.8509,
            -46.1808,
            172.5,
            -97.8509,
            -56.1808,
            168.75,
            -85.5184,
            -56.1808,
            168.75,
            107.74,
            -48.6808,
            168.75,
            107.74,
            -48.6808,
            168.75,
            -85.5184,
            -48.7279,
            47.3393,
            90.567,
            -48.7279,
            47.3393,
            -68.0447,
            -56.2009,
            47.3393,
            90.567,
            -56.2009,
            47.3393,
            -68.0447,
            -46.1808,
            172.5,
            120.072,
            -46.1808,
            172.5,
            107.74,
            -58.6808,
            172.5,
            120.072,
            -58.6808,
            172.5,
            107.74,
            -36.012,
            194.557,
            -16.778,
            -348.123,
            -2.02097,
            -30.2718,
            -353.246,
            6.56318,
            -30.0062,
            -30.8892,
            185.973,
            -17.0436,
            -357.48,
            2.65118,
            32.6561,
            -33.9298,
            186.509,
            40.9611,
            -39.0526,
            195.093,
            41.2267,
            -352.357,
            -5.93296,
            32.3905,
            -34.3429,
            194.966,
            -84.0146,
            -345.79,
            -2.84314,
            -94.5455,
            -350.938,
            5.72977,
            -94.5638,
            -29.1945,
            186.393,
            -83.9963,
            -355.683,
            3.56822,
            -31.8532,
            -32.7194,
            188.551,
            -26.0567,
            -37.8679,
            197.123,
            -26.0749,
            -350.535,
            -5.00469,
            -31.835,
            -353.611,
            1.13564,
            103.246,
            -34.4486,
            186.494,
            107.254,
            -39.6819,
            195.013,
            107.039,
            -348.378,
            -7.38301,
            103.461,
            -35.7867,
            196.379,
            44.2473,
            -348.861,
            -4.96683,
            45.4267,
            -354.095,
            3.55181,
            45.2118,
            -30.5533,
            187.861,
            44.4622,
            -58.6808,
            172.5,
            -85.5183,
            -46.1808,
            7.48031e-7,
            -85.5183,
            -46.1808,
            172.5,
            -85.5183,
            -58.6808,
            7.47332e-7,
            -85.5183,
            -58.6808,
            3.41989e-7,
            -97.8509,
            -58.6808,
            172.5,
            -97.8509,
            -46.1808,
            3.42688e-7,
            -97.8509,
            -46.1808,
            172.5,
            -97.8509,
            -58.6808,
            0,
            107.74,
            -58.6808,
            172.5,
            107.74,
            -46.1808,
            6.99307e-10,
            107.74,
            -46.1808,
            172.5,
            107.74,
            -58.6808,
            172.5,
            120.072,
            -46.1808,
            5.98203e-7,
            120.072,
            -46.1808,
            172.5,
            120.072,
            -58.6808,
            5.97503e-7,
            120.072,
            -56.2009,
            161.25,
            90.567,
            -56.2009,
            161.25,
            -68.0447,
            -48.7279,
            161.25,
            90.567,
            -48.7279,
            161.25,
            -68.0447,
            -56.1808,
            39.8393,
            107.74,
            -48.6808,
            39.8393,
            -85.5184,
            -48.6808,
            39.8393,
            107.74,
            -56.1808,
            39.8393,
            -85.5184,
            -33.9298,
            186.509,
            40.9611,
            -352.357,
            -5.93296,
            32.3905,
            -348.123,
            -2.02097,
            -30.2718,
            -30.8892,
            185.973,
            -17.0436,
            -32.7194,
            188.551,
            -26.0567,
            -350.535,
            -5.00469,
            -31.835,
            -345.79,
            -2.84314,
            -94.5455,
            -29.1945,
            186.393,
            -83.9963,
            -348.861,
            -4.96683,
            45.4267,
            -34.4486,
            186.494,
            107.254,
            -348.378,
            -7.38301,
            103.461,
            -30.5533,
            187.861,
            44.4622,
            -56.2009,
            98.1522,
            8.27449,
            -56.2009,
            47.3393,
            -68.0447,
            -48.7279,
            98.1522,
            8.27449,
            -48.7279,
            47.3393,
            -68.0447,
            -56.2009,
            47.3393,
            90.567,
            -48.7279,
            98.1522,
            8.27449,
            -48.7279,
            47.3393,
            90.567,
            -56.2009,
            98.1522,
            8.27449,
            -56.2009,
            161.25,
            107.74,
            -56.2009,
            104.294,
            14.1033,
            -48.7279,
            161.25,
            107.74,
            -48.7279,
            104.294,
            14.1033,
            -48.7279,
            161.25,
            -85.5184,
            -48.7279,
            104.294,
            2.44572,
            -56.2009,
            104.294,
            2.44572,
            -56.2009,
            161.25,
            -85.5184
          ]
        },
        "normal": {
          "type": "float32",
          "components": 3,
          "data": [
            0.858563,
            0.511123,
            0.0402795,
            0.858563,
            0.511123,
            0.0402795,
            0.858563,
            0.511123,
            0.0402795,
            0.858563,
            0.511123,
            0.0402795,
            -0.856475,
            -0.508351,
            -0.0896077,
            -0.856475,
            -0.508351,
            -0.0896077,
            -0.856475,
            -0.508351,
            -0.0896077,
            -0.856475,
            -0.508351,
            -0.0896077,
            0.85679,
            0.514612,
            0.0329613,
            0.85679,
            0.514612,
            0.0329613,
            0.85679,
            0.514612,
            0.0329613,
            0.85679,
            0.514612,
            0.0329613,
            -0.8543,
            -0.513219,
            -0.0823291,
            -0.8543,
            -0.513219,
            -0.0823291,
            -0.8543,
            -0.513219,
            -0.0823291,
            -0.8543,
            -0.513219,
            -0.0823291,
            -0.851797,
            -0.523665,
            -0.0146995,
            -0.851797,
            -0.523665,
            -0.0146995,
            -0.851797,
            -0.523665,
            -0.0146995,
            -0.851797,
            -0.523665,
            -0.0146995,
            0.84958,
            0.523551,
            0.0641001,
            0.84958,
            0.523551,
            0.0641001,
            0.84958,
            0.523551,
            0.0641001,
            0.84958,
            0.523551,
            0.0641001,
            -1,
            0,
            0,
            -1,
            0,
            0,
            -1,
            0,
            0,
            -1,
            0,
            0,
            -1,
            0,
            0,
            -1,
            0,
            0,
            -1,
            0,
            0,
            -1,
            0,
            0,
            -0.999999,
            0.00148453,
            -1.24419e-8,
            -1,
            -1.80155e-8,
            0,
            -0.999998,
            0.00195991,
            -3.7117e-8,
            -1,
            -1.66283e-8,
            0,
            -1,
            0,
            0,
            -1,
            0,
            0,
            -0.999996,
            0.00268303,
            0,
            -0.999996,
            0.00268431,
            0,
            -0.999996,
            0.00268431,
            0,
            -0.999998,
            -0.00181573,
            -2.58442e-8,
            -0.999999,
            -0.00148455,
            -9.44807e-9,
            -0.999996,
            -0.00268284,
            0,
            -1,
            0,
            0,
            -1,
            0,
            0,
            -0.999996,
            -0.00268357,
            0,
            -0.999996,
            -0.00268357,
            0,
            -0.999999,
            0.00127917,
            7.33417e-9,
            -1,
            0,
            0,
            -1,
            0,
            0,
            -0.999999,
            0.00151035,
            1.16203e-8,
            -0.999996,
            0.00268219,
            0,
            -0.999999,
            -0.00165411,
            6.12636e-9,
            -1,
            4.45839e-7,
            0,
            -0.999999,
            -0.00127878,
            7.97445e-9,
            -1,
            4.45839e-7,
            0,
            -0.999996,
            -0.00268219,
            0,
            0,
            0.850866,
            -0.525382,
            0,
            0.850866,
            -0.525382,
            0,
            0.850866,
            -0.525382,
            0,
            0.850866,
            -0.525382,
            0,
            0.832385,
            0.554198,
            0,
            0.832385,
            0.554198,
            0,
            0.832385,
            0.554198,
            0,
            0.832385,
            0.554198,
            0,
            0.839409,
            -0.5435,
            0,
            0.839409,
            -0.5435,
            0,
            0.839409,
            -0.5435,
            0,
            0.839409,
            -0.5435,
            0,
            0.854366,
            0.519671,
            0,
            0.854366,
            0.519671,
            0,
            0.854366,
            0.519671,
            0,
            0.854366,
            0.519671,
            -0.508437,
            0.860404,
            -0.0346033,
            -0.508429,
            0.860407,
            -0.0346318,
            -0.508432,
            0.860406,
            -0.0346191,
            -0.508437,
            0.860404,
            -0.0346,
            -0.510494,
            0.857571,
            -0.0629882,
            -0.510495,
            0.857572,
            -0.0629693,
            -0.510489,
            0.857573,
            -0.0630041,
            -0.510494,
            0.857572,
            -0.0629849,
            -0.525387,
            0.849933,
            0.0397778,
            -0.525383,
            0.849936,
            0.0397618,
            -0.525389,
            0.849931,
            0.0397906,
            -0.525383,
            0.849936,
            0.0397585,
            0,
            1,
            0,
            0,
            1,
            0,
            0,
            1,
            0,
            0,
            1,
            0,
            0,
            1,
            0,
            0,
            1,
            0,
            0,
            1,
            0,
            0,
            1,
            0,
            0,
            1,
            0,
            0,
            1,
            0,
            0,
            1,
            0,
            0,
            1,
            0,
            0,
            1,
            0,
            0,
            1,
            0,
            0,
            1,
            0,
            0,
            1,
            0,
            0.0172428,
            0.0411986,
            -0.999002,
            0.0172428,
            0.0411986,
            -0.999002,
            0.0172428,
            0.0411986,
            -0.999002,
            0.0172428,
            0.0411986,
            -0.999002,
            -0.00603537,
            -0.0345223,
            0.999386,
            -0.00603537,
            -0.0345223,
            0.999386,
            -0.00603537,
            -0.0345223,
            0.999386,
            -0.00603537,
            -0.0345223,
            0.999386,
            0.0254468,
            0.0131505,
            -0.99959,
            0.0254468,
            0.0131505,
            -0.99959,
            0.0254468,
            0.0131505,
            -0.99959,
            0.0254468,
            0.0131505,
            -0.99959,
            -0.0142613,
            -0.00643292,
            0.999878,
            -0.0142613,
            -0.00643292,
            0.999878,
            -0.0142613,
            -0.00643292,
            0.999878,
            -0.0142613,
            -0.00643292,
            0.999878,
            -0.0200462,
            0.0129043,
            0.999716,
            -0.0200462,
            0.0129043,
            0.999716,
            -0.0200462,
            0.0129043,
            0.999716,
            -0.0200462,
            0.0129043,
            0.999716,
            0.00892682,
            -0.0197361,
            -0.999765,
            0.00892682,
            -0.0197361,
            -0.999765,
            0.00892682,
            -0.0197361,
            -0.999765,
            0.00892682,
            -0.0197361,
            -0.999765,
            0,
            0,
            1,
            0,
            0,
            1,
            0,
            0,
            1,
            0,
            0,
            1,
            -3.17338e-11,
            0,
            -1,
            -3.17338e-11,
            0,
            -1,
            -3.17338e-11,
            0,
            -1,
            -3.17338e-11,
            0,
            -1,
            3.49417e-11,
            0,
            -1,
            3.49417e-11,
            0,
            -1,
            3.49417e-11,
            0,
            -1,
            3.49417e-11,
            0,
            -1,
            0,
            0,
            1,
            0,
            0,
            1,
            0,
            0,
            1,
            0,
            0,
            1,
            0,
            -1,
            0,
            0,
            -1,
            0,
            0,
            -1,
            0,
            0,
            -1,
            0,
            0,
            -1,
            0,
            0,
            -1,
            0,
            0,
            -1,
            0,
            0,
            -1,
            0,
            0.517505,
            -0.855481,
            -0.0184402,
            0.517505,
            -0.855482,
            -0.0184257,
            0.51751,
            -0.855478,
            -0.0184569,
            0.517507,
            -0.85548,
            -0.0184434,
            0.51999,
            -0.854115,
            0.00990333,
            0.519989,
            -0.854115,
            0.00991781,
            0.519995,
            -0.854112,
            0.00988659,
            0.519991,
            -0.854114,
            0.00990012,
            0.518116,
            -0.855204,
            0.0135257,
            0.518111,
            -0.855206,
            0.0135426,
            0.518115,
            -0.855204,
            0.013529,
            0.518116,
            -0.855204,
            0.0135112,
            0,
            -0.832385,
            0.554198,
            0,
            -0.832385,
            0.554198,
            0,
            -0.832385,
            0.554198,
            0,
            -0.832385,
            0.554198,
            0,
            -0.850866,
            -0.525382,
            0,
            -0.850866,
            -0.525382,
            0,
            -0.850866,
            -0.525382,
            0,
            -0.850866,
            -0.525382,
            0,
            -0.854362,
            0.519678,
            0,
            -0.854362,
            0.519678,
            0,
            -0.854362,
            0.519678,
            0,
            -0.854362,
            0.519678,
            0,
            -0.839405,
            -0.543506,
            0,
            -0.839405,
            -0.543506,
            0,
            -0.839405,
            -0.543506,
            0,
            -0.839405,
            -0.543506
          ]
        },
        "color": {
          "type": "uint8",
          "components": 4,
          "data": [
            233,
            232,
            232,
            255,
            233,
            232,
            232,
            255,
            233,
            232,
            232,
            255,
            233,
            232,
            232,
            255,
            233,
            232,
            232,
            255,
            233,
            232,
            232,
            255,
            233,
            232,
            232,
            255,
            233,
            232,
            232,
            255,
            233,
            232,
            232,
            255,
            233,
            232,
            232,
            255,
            233,
            232,
            232,
            255,
            233,
            232,
            232,
            255,
            233,
            232,
            232,
            255,
            233,
            232,
            232,
            255,
            233,
            232,
            232,
            255,
            233,
            232,
            232,
            255,
            233,
            232,
            232,
            255,
            233,
            232,
            232,
            255,
            233,
            232,
            232,
            255,
            233,
            232,
            232,
            255,
            233,
            232,
            232,
            255,
            233,
            232,
            232,
            255,
            233,
            232,
            232,
            255,
            233,
            232,
            232,
            255,
            89,
            71,
            89,
            255,
            233,
            232,
            232,
            255,
            89,
            71,
            89,
            255,
            233,
            232,
            232,
            255,
            233,
            232,
            232,
            255,
            89,
            71,
            89,
            255,
            89,
            71,
            89,
            255,
            233,
            232,
            232,
            255,
            89,
            71,
            89,
            255,
            233,
            232,
            232,
            255,
            89,
            71,
            89,
            255,
            233,
            232,
            232,
            255,
            233,
            232,
            232,
            255,
            233,
            232,
            232,
            255,
            89,
            71,
            89,
            255,
            89,
            71,
            89,
            255,
            89,
            71,
            89,
            255,
            233,
            232,
            232,
            255,
            233,
            232,
            232,
            255,
            233,
            232,
            232,
            255,
            233,
            232,
            232,
            255,
            233,
            232,
            232,
            255,
            233,
            232,
            232,
            255,
            233,
            232,
            232,
            255,
            89,
            71,
            89,
            255,
            233,
            232,
            232,
            255,
            233,
            232,
            232,
            255,
            89,
            71,
            89,
            255,
            89,
            71,
            89,
            255,
            233,
            232,
            232,
            255,
            233,
            232,
            232,
            255,
            233,
            232,
            232,
            255,
            233,
            232,
            232,
            255,
            233,
            232,
            232,
            255,
            89,
            71,
            89,
            255,
            233,
            232,
            232,
            255,
            89,
            71,
            89,
            255,
            233,
            232,
            232,
            255,
            89,
            71,
            89,
            255,
            233,
            232,
            232,
            255,
            233,
            232,
            232,
            255,
            89,
            71,
            89,
            255,
            233,
            232,
            232,
            255,
            233,
            232,
            232,
            255,
            233,
            232,
            232,
            255,
            233,
            232,
            232,
            255,
            233,
            232,
            232,
            255,
            233,
            232,
            232,
            255,
            233,
            232,
            232,
            255,
            233,
            232,
            232,
            255,
            233,
            232,
            232,
            255,
            233,
            232,
            232,
            255,
            233,
            232,
            232,
            255,
            233,
            232,
            232,
            255,
            233,
            232,
            232,
            255,
            233,
            232,
            232,
            255,
            233,
            232,
            232,
            255,
            233,
            232,
            232,
            255,
            233,
            232,
            232,
            255,
            233,
            232,
            232,
            255,
            233,
            232,
            232,
            255,
            233,
            232,
            232,
            255,
            89,
            71,
            89,
            255,
            89,
            71,
            89,
            255,
            89,
            71,
            89,
            255,
            89,
            71,
            89,
            255,
            89,
            71,
            89,
            255,
            89,
            71,
            89,
            255,
            89,
            71,
            89,
            255,
            89,
            71,
            89,
            255,
            233,
            232,
            232,
            255,
            233,
            232,
            232,
            255,
            233,
            232,
            232,
            255,
            233,
            232,
            232,
            255,
            89,
            71,
            89,
            255,
            89,
            71,
            89,
            255,
            89,
            71,
            89,
            255,
            89,
            71,
            89,
            255,
            170,
            145,
            170,
            255,
            170,
            145,
            170,
            255,
            170,
            145,
            170,
            255,
            170,
            145,
            170,
            255,
            170,
            145,
            170,
            255,
            170,
            145,
            170,
            255,
            170,
            145,
            170,
            255,
            170,
            145,
            170,
            255,
            170,
            145,
            170,
            255,
            170,
            145,
            170,
            255,
            170,
            145,
            170,
            255,
            170,
            145,
            170,
            255,
            170,
            145,
            170,
            255,
            170,
            145,
            170,
            255,
            170,
            145,
            170,
            255,
            170,
            145,
            170,
            255,
            170,
            145,
            170,
            255,
            170,
            145,
            170,
            255,
            170,
            145,
            170,
            255,
            170,
            145,
            170,
            255,
            170,
            145,
            170,
            255,
            170,
            145,
            170,
            255,
            170,
            145,
            170,
            255,
            170,
            145,
            170,
            255,
            89,
            71,
            89,
            255,
            170,
            145,
            170,
            255,
            89,
            71,
            89,
            255,
            170,
            145,
            170,
            255,
            170,
            145,
            170,
            255,
            89,
            71,
            89,
            255,
            170,
            145,
            170,
            255,
            89,
            71,
            89,
            255,
            170,
            145,
            170,
            255,
            89,
            71,
            89,
            255,
            170,
            145,
            170,
            255,
            89,
            71,
            89,
            255,
            89,
            71,
            89,
            255,
            170,
            145,
            170,
            255,
            89,
            71,
            89,
            255,
            170,
            145,
            170,
            255,
            89,
            71,
            89,
            255,
            89,
            71,
            89,
            255,
            89,
            71,
            89,
            255,
            89,
            71,
            89,
            255,
            54,
            29,
            54,
            255,
            54,
            29,
            54,
            255,
            54,
            29,
            54,
            255,
            54,
            29,
            54,
            255,
            54,
            29,
            54,
            255,
            54,
            29,
            54,
            255,
            54,
            29,
            54,
            255,
            54,
            29,
            54,
            255,
            54,
            29,
            54,
            255,
            54,
            29,
            54,
            255,
            54,
            29,
            54,
            255,
            54,
            29,
            54,
            255,
            54,
            29,
            54,
            255,
            54,
            29,
            54,
            255,
            54,
            29,
            54,
            255,
            54,
            29,
            54,
            255,
            54,
            29,
            54,
            255,
            54,
            29,
            54,
            255,
            54,
            29,
            54,
            255,
            54,
            29,
            54,
            255,
            54,
            29,
            54,
            255,
            54,
            29,
            54,
            255,
            54,
            29,
            54,
            255,
            54,
            29,
            54,
            255,
            89,
            71,
            89,
            255,
            54,
            29,
            54,
            255,
            89,
            71,
            89,
            255,
            54,
            29,
            54,
            255,
            89,
            71,
            89,
            255,
            54,
            29,
            54,
            255,
            54,
            29,
            54,
            255,
            89,
            71,
            89,
            255
          ]
        },
        "texCoord0": {
          "type": "float32",
          "components": 2,
          "data": [
            0.463825,
            0.557114,
            0.478757,
            0.557114,
            0.478757,
            0.561347,
            0.463825,
            0.561347,
            0.478757,
            0.557114,
            0.463825,
            0.561347,
            0.478757,
            0.561347,
            0.463825,
            0.557114,
            0.478757,
            0.561347,
            0.463825,
            0.561347,
            0.463825,
            0.557114,
            0.478757,
            0.557114,
            0.463825,
            0.561347,
            0.478757,
            0.557114,
            0.463825,
            0.557114,
            0.478757,
            0.561347,
            0.463825,
            0.557114,
            0.478757,
            0.561347,
            0.463825,
            0.561347,
            0.478757,
            0.557114,
            0.463825,
            0.557114,
            0.478757,
            0.561347,
            0.478757,
            0.557114,
            0.463825,
            0.561347,
            0.989405,
            0.828101,
            0.993631,
            0.768992,
            0.993631,
            0.828101,
            0.989405,
            0.768992,
            0.989405,
            0.768992,
            0.989405,
            0.828101,
            0.993631,
            0.828101,
            0.993631,
            0.768992,
            0.938373,
            0.839722,
            0.968514,
            0.815423,
            0.943844,
            0.839722,
            0.970787,
            0.817399,
            0.970909,
            0.813579,
            0.97318,
            0.815553,
            0.93862,
            0.842162,
            0.999464,
            0.842166,
            0.99431,
            0.839722,
            0.943844,
            0.839722,
            0.938373,
            0.839722,
            0.93862,
            0.842162,
            0.968514,
            0.815423,
            0.970787,
            0.817399,
            0.999464,
            0.842166,
            0.99431,
            0.839722,
            0.943844,
            0.839722,
            0.970787,
            0.817399,
            0.968514,
            0.815423,
            0.938373,
            0.839722,
            0.93862,
            0.842162,
            0.938373,
            0.839722,
            0.968514,
            0.815423,
            0.943844,
            0.839722,
            0.970787,
            0.817399,
            0.93862,
            0.842162,
            0.950905,
            0.836927,
            0.970618,
            0.821244,
            0.943844,
            0.839722,
            0.970787,
            0.817399,
            0.943844,
            0.839722,
            0.970787,
            0.817399,
            0.970618,
            0.821244,
            0.950905,
            0.836927,
            0.964641,
            0.815289,
            0.936722,
            0.837578,
            0.968514,
            0.815423,
            0.938373,
            0.839722,
            0.936722,
            0.837578,
            0.964641,
            0.815289,
            0.938373,
            0.839722,
            0.968514,
            0.815423,
            0.478757,
            0.446584,
            0.494351,
            0.557114,
            0.478757,
            0.557114,
            0.494351,
            0.446584,
            0.478757,
            0.446584,
            0.494351,
            0.557114,
            0.478757,
            0.557114,
            0.494351,
            0.446584,
            0.478757,
            0.446584,
            0.478757,
            0.557114,
            0.463825,
            0.446584,
            0.463825,
            0.557114,
            0.989405,
            0.832384,
            0.989405,
            0.828101,
            0.993631,
            0.832384,
            0.993631,
            0.828101,
            0.93862,
            0.842162,
            0.999464,
            0.842166,
            0.999444,
            0.844839,
            0.938601,
            0.844839,
            0.987767,
            0.836934,
            0.950905,
            0.836927,
            0.99431,
            0.839722,
            0.943844,
            0.839722,
            0.989405,
            0.828101,
            0.993631,
            0.828101,
            0.989405,
            0.832384,
            0.993631,
            0.832384,
            0.463825,
            0.557114,
            0.460238,
            0.446584,
            0.463825,
            0.446584,
            0.460238,
            0.557114,
            0.460238,
            0.446584,
            0.463825,
            0.557114,
            0.460238,
            0.557114,
            0.463825,
            0.446584,
            0.460238,
            0.446584,
            0.463825,
            0.557114,
            0.460238,
            0.557114,
            0.463825,
            0.446584,
            0.463825,
            0.557114,
            0.460238,
            0.446584,
            0.463825,
            0.446584,
            0.460238,
            0.557114,
            0.463825,
            0.557114,
            0.460238,
            0.446584,
            0.463825,
            0.446584,
            0.460238,
            0.557114,
            0.460238,
            0.446584,
            0.463825,
            0.557114,
            0.460238,
            0.557114,
            0.463825,
            0.446584,
            0.993631,
            0.828101,
            0.99791,
            0.768992,
            0.99791,
            0.828101,
            0.993631,
            0.768992,
            0.989405,
            0.768992,
            0.989405,
            0.828101,
            0.985118,
            0.768992,
            0.985118,
            0.828101,
            0.993631,
            0.768992,
            0.993631,
            0.828101,
            0.99791,
            0.768992,
            0.99791,
            0.828101,
            0.989405,
            0.828101,
            0.985118,
            0.768992,
            0.985118,
            0.828101,
            0.989405,
            0.768992,
            0.99431,
            0.839722,
            0.943844,
            0.839722,
            0.987767,
            0.836934,
            0.950905,
            0.836927,
            0.999464,
            0.842166,
            0.938601,
            0.844839,
            0.999444,
            0.844839,
            0.93862,
            0.842162,
            0.491336,
            0.308725,
            0.380805,
            0.308725,
            0.380805,
            0.295202,
            0.491336,
            0.295202,
            0.380805,
            0.295204,
            0.491336,
            0.295204,
            0.491336,
            0.308725,
            0.380805,
            0.308725,
            0.491336,
            0.308725,
            0.380805,
            0.295202,
            0.491336,
            0.295202,
            0.380805,
            0.308725,
            0.970787,
            0.817399,
            0.943844,
            0.839722,
            0.970618,
            0.821244,
            0.950905,
            0.836927,
            0.943844,
            0.839722,
            0.970618,
            0.821244,
            0.950905,
            0.836927,
            0.970787,
            0.817399,
            0.938373,
            0.839722,
            0.968514,
            0.815423,
            0.936722,
            0.837578,
            0.964641,
            0.815289,
            0.936722,
            0.837578,
            0.964641,
            0.815289,
            0.968514,
            0.815423,
            0.938373,
            0.839722
          ]
        }
      }
    ],
    "meshes": [
      {
        "aabb": {
          "min": [
            -357.48,
            -7.38301,
            -97.8509
          ],
          "max": [
            -29.1945,
            197.123,
            120.072
          ]
        },
        "vertices": 0,
        "indices": [
          0,
          1,
          2,
          2,
          3,
          0,
          4,
          5,
          6,
          5,
          4,
          7,
          8,
          9,
          10,
          10,
          11,
          8,
          12,
          13,
          14,
          13,
          12,
          15,
          16,
          17,
          18,
          17,
          16,
          19,
          20,
          21,
          22,
          21,
          20,
          23,
          24,
          25,
          26,
          25,
          24,
          27,
          28,
          29,
          30,
          28,
          30,
          31,
          32,
          33,
          34,
          34,
          33,
          35,
          33,
          36,
          37,
          33,
          37,
          35,
          38,
          32,
          34,
          39,
          38,
          34,
          39,
          34,
          40,
          41,
          42,
          43,
          41,
          44,
          42,
          44,
          41,
          45,
          46,
          41,
          43,
          41,
          46,
          47,
          48,
          49,
          50,
          50,
          51,
          48,
          48,
          51,
          52,
          53,
          54,
          55,
          56,
          55,
          54,
          57,
          53,
          55,
          58,
          59,
          60,
          60,
          59,
          61,
          62,
          63,
          64,
          64,
          65,
          62,
          66,
          67,
          68,
          68,
          67,
          69,
          70,
          71,
          72,
          72,
          71,
          73,
          74,
          75,
          76,
          75,
          74,
          77,
          78,
          79,
          80,
          79,
          78,
          81,
          82,
          83,
          84,
          85,
          84,
          83,
          86,
          87,
          88,
          87,
          89,
          88,
          90,
          91,
          92,
          92,
          93,
          90,
          94,
          95,
          96,
          96,
          95,
          97,
          98,
          99,
          100,
          100,
          99,
          101,
          102,
          103,
          104,
          103,
          102,
          105,
          106,
          107,
          108,
          107,
          106,
          109,
          110,
          111,
          112,
          111,
          110,
          113,
          114,
          115,
          116,
          115,
          114,
          117,
          118,
          119,
          120,
          119,
          118,
          121,
          122,
          123,
          124,
          123,
          122,
          125,
          126,
          127,
          128,
          127,
          126,
          129,
          130,
          131,
          132,
          132,
          131,
          133,
          134,
          135,
          136,
          136,
          135,
          137,
          138,
          139,
          140,
          139,
          138,
          141,
          142,
          143,
          144,
          144,
          143,
          145,
          146,
          147,
          148,
          147,
          146,
          149,
          150,
          151,
          152,
          150,
          152,
          153,
          154,
          155,
          156,
          154,
          156,
          157,
          158,
          159,
          160,
          159,
          158,
          161,
          162,
          163,
          164,
          164,
          163,
          165,
          166,
          167,
          168,
          167,
          166,
          169,
          170,
          171,
          172,
          172,
          171,
          173,
          174,
          175,
          176,
          176,
          177,
          174
        ],
        "type": "triangles",
        "base": 0,
        "count": 282
      }
    ],
    "meshInstances": [
      {
        "node": 1,
        "mesh": 0
      }
    ]
  }
}