{
  "id": "121",
  "title": "Angry Checkers",
  "slug": "angry-checkers",
  "description": "Common checkers are boring? Try angry checkers! Try to beat enemy checkers out of the board. there are 3 game modes. 1. Multiplayer - you play versus another random player via internet. 2. Single Player - you play versus AI. 3. Hot Seat - you play versus your friend on the same device.",
  "instructions": "Touch Mouse",
  "url": "https://html5.gamemonetize.com/skma0pcrooj5rpuhitzk7etjqfsctr3l/",
  "category": ".IO",
  "categorySlug": "io",
  "tags": [
    "2 Player",
    "Action",
    "Arena",
    "IO",
    "Multiplayer"
  ],
  "thumb": "https://img.gamemonetize.com/skma0pcrooj5rpuhitzk7etjqfsctr3l/512x384.jpg",
  "width": 960,
  "height": 640,
  "publisher": "zigziGames",
  "crawledAt": "2026-01-30T10:23:14.816Z"
}